{
  "Login": "ورود به سیستم",
  "Name": "نام",
  "User name": "نام کاربری",
  "Password": "کلمه عبور",
  "Confirm password": "تایید کلمه عبور",
  "Entry": "ورود",
  "Register": "ثبت نام",
  "This field is required": "این فیلد اجباری است",
  "This field should be at least 3 character": "این فیلد باید حداقل 3 کاراکتر باشد",
  "This field should be at least 6 character": "این فیلد باید حداقل 6 کاراکتر باشد",
  "Password and Confirm password do not match": "کلمه عبور و تایید کلمه عبور یکسان نیستند",
  "The username is duplicated": "نام کاربری تکراری است",
  "Username or password in incorrect": "نام کاربری یا کلمه عبور صحیح نیست",
  "The code is required": "کد اجباری است",
  "The code is duplicated": "کد تکراری است",
  "The title is required": "عنوان اجباری است",
  "The title should have at least 3 character": "عنوان باید حداقل 3 کاراکتر داشته باشد",
  "The Current Account has Subsidiary ledger account": "حساب جاری دارای معین میباشد",
  "The current period is closed , You are not allowed to create Journal": "دوره جاری بسته شده ، امکان ایجاد سند وجود ندارد",
  "The current period is closed , You are not allowed to edit Journal": "دوره جاری بسته شده ، امکان ویرایش سند وجود ندارد",
  "The current period is closed , You are not allowed to delete Journal": "دوره جاری بسته شده ، امکان حذف سند وجود ندارد",
  "The current journal is fixed , You are not allowed to delete it": "سند ثبت قطعی شده ، امکان خذف وجود ندارد",
  "The current journal is fixed , You are not allowed to edit it": "سند ثبت قطعی شده ، امکان خذف وجود ندارد",
  "The journal with this TemporaryNumber already created": "سندی با شماره موقت وارد شده قبلا ایجاد شده",
  "The temporaryDate is not in current period date range": "تاریخ در دوره جاری نیست",
  "This journal is already fixed": "این سند قبلا ثبت قطعی شده",
  "The Article is required": "شرح آرتیکل اجباری است",
  "Pages": "برگی",
  "From": "از",
  "To": "تا",
  "Page": "صفحه",
  "Report organization title": "شرکت فراز رایانه کیهان",
  "Report department title": "امور مالی",
  "Report title": "سند حسابداری",
  "Creator": "تهیه کننده",
  "Report designer": "طراحی گزارش",
  "The detailAccount is not define": "حساب تفضیل تعریف نشده است",
  "The Dimension1 is not define": "حساب تفضیل1 تعریف نشده است",
  "The Dimension2 is not define": "حساب تفضیل2 تعریف نشده است",
  "The Dimension3 is not define": "حساب تفضیل3 تعریف نشده است",
  "Debtor and creditor are not allowed to be zero , both of them":"بدهکار و بستانکار هر دو نباید صفر باشد",
  "The Subsidiary ledger account is used on journal": "معین جاری در اسناد حسابداری استفاده شده ",
  "Debtor and creditor are not allowed to have value , both of them": "بدهکار و بستانکار نباید هر دو دارای مقدار باشد",
  "From date can not be greater than to date":"تاریخ پایان دوره نمیتواند از تاریخ آغاز دوره کوچکتر باشد",

  "For payment invoice number ...":"بابت پرداخت فاکتور شماره {0}",

  "For Cash sale invoice number ...":"بابت فاکتور فروش شماره {0}",
  "received payment for invoice number ... ": "دریافت وجه بابت فاکتور شماره {0}",
  "received cash for invoice number ... ": "دریافت وجه نقد بابت فاکتور شماره {0}",
  "received receipt number ... for invoice number ... ": "دریافت فیش / رسید شماره {0} بابت فاکتور شماره {1}",
  "received cheque number ... date ... bank ... branch ... for invoice number ... ": "دریافت چک شماره {0} سررسید {1} بانک {2} شعبه {3} بابت فاکتور شماره {4}",

  "For Cash purchase invoice number ...":"بابت فاکتور خرید شماره {0}",
  "paid payment for invoice number ... ": "پرداخت وجه بابت فاکتور شماره {0}",
  "paid cash for invoice number ... ": "پرداخت وجه نقد بابت فاکتور شماره {0}",
  "paid receipt number ... for invoice number ... ": "پرداخت فیش / رسید شماره {0} بابت فاکتور شماره {1}",
  "paid cheque number ... date ... bank ... branch ... for invoice number ... ": "پرداخت چک شماره {0} سررسید {1} بانک {2} شعبه {3} بابت فاکتور شماره {4}",
  "Transfer money from ... to ...": "بابت انتقال وجه از {0} به {1}",

  "passed cheque number ... date ... bank ... branch ...": "بابت وصول چک شماره {0} سررسید {1} بانک {2} شعبه {3}",
  "returned cheque number ... date ... bank ... branch ...": "بابت عودت چک شماره {0} سررسید {1} بانک {2} شعبه {3}"
}
